outlook_calendar_sync/__init__.py
outlook_calendar_sync/__main__.py
outlook_calendar_sync/application.py
outlook_calendar_sync/cli.py
outlook_calendar_sync/gcal.py
outlook_calendar_sync/outlook.py
outlook_calendar_sync/utils.py
outlook_calendar_sync-0.0.5.dist-info/AUTHORS.rst
outlook_calendar_sync-0.0.5.dist-info/LICENSE
outlook_calendar_sync-0.0.5.dist-info/METADATA
outlook_calendar_sync-0.0.5.dist-info/WHEEL
outlook_calendar_sync-0.0.5.dist-info/entry_points.txt
outlook_calendar_sync-0.0.5.dist-info/top_level.txt
outlook_calendar_sync-0.0.5.dist-info/RECORD
