Metadata-Version: 2.1
Name: outlook-calendar-sync
Version: 0.0.5
Summary: CLI interface to scrape outlook calendar events from the webapp and insert them to a google calendar account.
Home-page: https://github.com/mr55p-dev/python-outlook-calendar-sync
Author: Ellis Lunnon
Author-email: ellislunnon@gmail.com
License: BSD-2-Clause
Project-URL: Documentation, https://python-outlook-calendar-sync.readthedocs.io/
Project-URL: Changelog, https://python-outlook-calendar-sync.readthedocs.io/en/latest/changelog.html
Project-URL: Issue Tracker, https://github.com/mr55p-dev/python-outlook-calendar-sync/issues
Keywords: outlook,calendar,gcal,office365,web-scraping,selenium,cli
Classifier: Development Status :: 5 - Production/Stable
Classifier: Intended Audience :: Developers
Classifier: License :: OSI Approved :: BSD License
Classifier: Operating System :: Unix
Classifier: Operating System :: POSIX
Classifier: Operating System :: Microsoft :: Windows
Classifier: Programming Language :: Python
Classifier: Programming Language :: Python :: 3
Classifier: Programming Language :: Python :: 3 :: Only
Classifier: Programming Language :: Python :: 3.10
Classifier: Programming Language :: Python :: 3.11
Classifier: Programming Language :: Python :: Implementation :: CPython
Classifier: Topic :: Utilities
Requires-Python: >=3.10
License-File: LICENSE
License-File: AUTHORS.rst
Requires-Dist: selenium (>=4.6)
Requires-Dist: beautifulsoup4 (>=4.11)
Requires-Dist: google-api-python-client
Requires-Dist: google-auth-httplib2
Requires-Dist: google-auth-oauthlib
Provides-Extra: dev
Requires-Dist: pytest ; extra == 'dev'
Requires-Dist: bump2version ; extra == 'dev'
Requires-Dist: twine ; extra == 'dev'
Requires-Dist: flake8 ; extra == 'dev'
Requires-Dist: black ; extra == 'dev'
